{
  "eyebrow": "From the Steelworks Center of the West Archives",
  "title": "Historic Photos Gallery",
  "intro": "Browse our gallery of select historic photos. Tap to view larger. ",
  "items": [
    {
      "image": "images/admin-building-1902.jpg",
      "alt": "Admin Building 1902",
      "title": "Admin Building 1902",
      "description": "Credit Steelwork Center Archives "
    },
    {
      "image": "images/building-with-people-and-vehicles.jpg",
      "alt": "Admin Building with People and Vehicles",
      "title": "Admin Building with People and Vehicles",
      "description": "Credit Steelwork Center Archives "
    },
    {
      "image": "images/canning-peaches-1918.jpg",
      "alt": "Canning Peaches 1918",
      "title": "Canning Peaches 1918",
      "description": "Credit Steelwork Center Archives "
    },
    {
      "image": "images/cfi_pla_bof_0001_access.jpg",
      "alt": "Basic Oxygen Furnace (BOF)",
      "title": "Basic Oxygen Furnace (BOF)",
      "description": "Credit Steelwork Center Archives "
    },
    {
      "image": "images/cfistacks01.jpg",
      "alt": "Blast Furnace Row",
      "title": "Blast Furnace Row",
      "description": "Credit Steelwork Center Archives "
    },
    {
      "image": "images/cfistacks02.jpg",
      "alt": " Blast Furnace with Skip Hoist and Row of Hot Blast Stoves",
      "title": " Blast Furnace with Skip Hoist and Row of Hot Blast Stoves",
      "description": "Credit Steelwork Center Archives "
    },
    {
      "image": "images/coke-plant-at-night.jpg",
      "alt": "Cole Plant at Night",
      "title": "Cole Plant at Night",
      "description": "Credit Steelwork Center Archives "
    },
    {}
  ]
}